aspose_ocr_cloud/__init__.py
aspose_ocr_cloud/api_client.py
aspose_ocr_cloud/api_response.py
aspose_ocr_cloud/configuration.py
aspose_ocr_cloud/exceptions.py
aspose_ocr_cloud/py.typed
aspose_ocr_cloud/rest.py
aspose_ocr_cloud/api/__init__.py
aspose_ocr_cloud/api/binarize_image_api.py
aspose_ocr_cloud/api/convert_text_to_speech_api.py
aspose_ocr_cloud/api/convert_text_to_speech_trial_api.py
aspose_ocr_cloud/api/deskew_image_api.py
aspose_ocr_cloud/api/detect_regions_api.py
aspose_ocr_cloud/api/dewarp_image_api.py
aspose_ocr_cloud/api/dj_vu2_pdf_api.py
aspose_ocr_cloud/api/identify_font_api.py
aspose_ocr_cloud/api/image_processing_api.py
aspose_ocr_cloud/api/recognize_and_parse_invoice_api.py
aspose_ocr_cloud/api/recognize_image_api.py
aspose_ocr_cloud/api/recognize_image_trial_api.py
aspose_ocr_cloud/api/recognize_label_api.py
aspose_ocr_cloud/api/recognize_pdf_api.py
aspose_ocr_cloud/api/recognize_receipt_api.py
aspose_ocr_cloud/api/recognize_regions_api.py
aspose_ocr_cloud/api/recognize_table_api.py
aspose_ocr_cloud/api/text_to_speech_api.py
aspose_ocr_cloud/api/upscale_image_api.py
aspose_ocr_cloud/api/utilities_api.py
aspose_ocr_cloud/models/__init__.py
aspose_ocr_cloud/models/dsr_confidence.py
aspose_ocr_cloud/models/dsr_mode.py
aspose_ocr_cloud/models/language.py
aspose_ocr_cloud/models/language_tts.py
aspose_ocr_cloud/models/ocr_binarize_image_body.py
aspose_ocr_cloud/models/ocr_deskew_image_body.py
aspose_ocr_cloud/models/ocr_detect_regions_body.py
aspose_ocr_cloud/models/ocr_dewarp_image_body.py
aspose_ocr_cloud/models/ocr_error.py
aspose_ocr_cloud/models/ocr_recognize_and_parse_invoice_body.py
aspose_ocr_cloud/models/ocr_recognize_font_body.py
aspose_ocr_cloud/models/ocr_recognize_image_body.py
aspose_ocr_cloud/models/ocr_recognize_label_body.py
aspose_ocr_cloud/models/ocr_recognize_pdf_body.py
aspose_ocr_cloud/models/ocr_recognize_receipt_body.py
aspose_ocr_cloud/models/ocr_recognize_regions_body.py
aspose_ocr_cloud/models/ocr_recognize_table_body.py
aspose_ocr_cloud-24.11.0.dist-info/LICENSE
aspose_ocr_cloud-24.11.0.dist-info/METADATA
aspose_ocr_cloud-24.11.0.dist-info/WHEEL
aspose_ocr_cloud-24.11.0.dist-info/top_level.txt
aspose_ocr_cloud-24.11.0.dist-info/RECORD
