Metadata-Version: 2.1
Name: aspose-ocr-cloud
Version: 24.11.0
Summary: Aspose OCR Cloud 5.0 API
Home-page: https://pypi.org/project/aspose-ocr-cloud/
Author: Aspose
Author-email: 
License: MIT
Keywords: Aspose,OCR,Aspose OCR Cloud 5.0 API
License-File: LICENSE
Requires-Dist: urllib3>=1.25.3
Requires-Dist: python-dateutil
Requires-Dist: pydantic
Requires-Dist: aenum
